{
    "MediaFile": {
        "Airing": {
            "Channel": {
                "IsChannelViewable": false,
                "ChannelLogoCount": 0,
                "StationID": 0,
                "IsChannelObject": true,
                "ChannelDescription": "",
                "ChannelNumber": "",
                "ChannelName": ""
            },
            "IsShowFirstRun": false,
            "ParentalRating": "",
            "RealWatchedStartTime": 0,
            "AiringID": 10807679,
            "AiringChannelNumber": "",
            "AiringChannelName": "",
            "ScheduleDuration": 5794120,
            "TrackNumber": 0,
            "ScheduleEndTime": 1389516096000,
            "AiringRatings": [
                "R",
                "R for strong bloody violence",
                "language and some sexuality/nudity"
            ],
            "IsNotManualOrFavorite": true,
            "RealWatchedEndTime": 0,
            "IsAiringHDTV": true,
            "WatchedEndTime": 0,
            "IsWatched": false,
            "AiringDuration": 5794120,
            "IsWatchedCompletely": false,
            "ExtraAiringDetails": "HDTV",
            "ScheduleStartTime": 1389510301880,
            "LatestWatchedTime": 1389510301880,
            "IsFavorite": false,
            "RecordingName": "",
            "IsManualRecord": false,
            "IsAiringObject": true,
            "Show": {
                "PeopleListInShow": [
                    "Sharni Vinson -- Erin",
                    "Nicholas Tucci -- Felix",
                    "Wendy Glenn -- Zee",
                    "AJ Bowen -- Crispian",
                    "Joe Swanberg -- Drake",
                    "Margaret Laney -- Kelly (as Sarah Myers)",
                    "Amy Seimetz -- Aimee",
                    "Ti West -- Tariq",
                    "Rob Moran -- Paul",
                    "Barbara Crampton -- Aubrey",
                    "L.C. Holt -- Lamb Mask",
                    "Simon Barrett -- Tiger Mask",
                    "Lane Hughes -- Fox Mask",
                    "Larry Fessenden -- Erik Harson",
                    "Calvin Reeder -- Officer Trubiano",
                    "Kate Lyn Sheil -- Talia (uncredited)",
                    "Adam Wingard",
                    "Simon Barrett",
                    "Keith Calder",
                    "Kim Sherman",
                    "Jessica Wu"
                ],
                "ShowCategoriesList": [
                    "Comedy",
                    "Horror",
                    "Thriller"
                ],
                "ShowRated": "R",
                "ShowSubCategory": "Horror",
                "ShowExternalID": "MF10807676",
                "ShowCategory": "Comedy",
                "ShowTitle": "You're Next",
                "ShowCategoriesString": "Comedy / Horror / Thriller",
                "ShowSeasonNumber": 0,
                "IsShowObject": true,
                "ShowYear": "2011",
                "ShowEpisode": "You're Next",
                "IsShowEPGDataUnique": true,
                "ShowExpandedRatings": "R for strong bloody violence and language and some sexuality/nudity",
                "ShowEpisodeNumber": 0,
                "OriginalAiringDate": 1377230400000,
                "ShowDuration": 5700000,
                "ShowParentalRating": "",
                "PeopleAndCharacterListInShow": [
                    "Sharni Vinson -- Erin",
                    "Nicholas Tucci -- Felix",
                    "Wendy Glenn -- Zee",
                    "AJ Bowen -- Crispian",
                    "Joe Swanberg -- Drake",
                    "Margaret Laney -- Kelly (as Sarah Myers)",
                    "Amy Seimetz -- Aimee",
                    "Ti West -- Tariq",
                    "Rob Moran -- Paul",
                    "Barbara Crampton -- Aubrey",
                    "L.C. Holt -- Lamb Mask",
                    "Simon Barrett -- Tiger Mask",
                    "Lane Hughes -- Fox Mask",
                    "Larry Fessenden -- Erik Harson",
                    "Calvin Reeder -- Officer Trubiano",
                    "Kate Lyn Sheil -- Talia (uncredited)",
                    "Adam Wingard",
                    "Simon Barrett",
                    "Keith Calder",
                    "Kim Sherman",
                    "Jessica Wu"
                ],
                "ShowMisc": "",
                "RolesInShow": [
                    "Actor",
                    "Actor",
                    "Actor",
                    "Actor",
                    "Actor",
                    "Actor",
                    "Actor",
                    "Actor",
                    "Actor",
                    "Actor",
                    "Actor",
                    "Actor",
                    "Actor",
                    "Actor",
                    "Actor",
                    "Actor",
                    "Director",
                    "Producer",
                    "Producer",
                    "Producer",
                    "Producer"
                ],
                "ShowLanguage": "und",
                "ShowDescription": "When the Davison family comes under attack during their wedding anniversary getaway, the gang of mysterious killers soon learns that one of victims harbors a secret talent for fighting back.\n ----\n",
                "PeopleInShow": "Sharni Vinson -- Erin, Nicholas Tucci -- Felix, Wendy Glenn -- Zee, AJ Bowen -- Crispian, Joe Swanberg -- Drake, Margaret Laney -- Kelly (as Sarah Myers), Amy Seimetz -- Aimee, Ti West -- Tariq, Rob Moran -- Paul, Barbara Crampton -- Aubrey, L.C. Holt -- Lamb Mask, Simon Barrett -- Tiger Mask, Lane Hughes -- Fox Mask, Larry Fessenden -- Erik Harson, Calvin Reeder -- Officer Trubiano, Kate Lyn Sheil -- Talia (uncredited), Adam Wingard, Simon Barrett, Keith Calder, Kim Sherman, Jessica Wu"
            },
            "WatchedStartTime": 0,
            "AiringTotalParts": 1,
            "ScheduleRecordingRecurrence": "",
            "AiringEndTime": 1389516096000,
            "RecordingQuality": "",
            "AiringPartNumber": 1,
            "WatchedDuration": 0,
            "IsDontLike": false,
            "AiringStartTime": 1389510301880,
            "AiringTitle": "You're Next",
            "AiringPremiereFinaleInfo": "",
            "IsShowReRun": true,
            "AiringAttributeList": [
                "HDTV"
            ]
        },
        "FileEndTime": 1389516096000,
        "IsPictureFile": false,
        "MediaFileRelativePath": "Movies/New/You're Next (2011).mp4",
        "MediaFileMetadataProperties": {
            "ExtendedRatings": "R for strong bloody violence, language and some sexuality/nudity",
            "MediaType": "Movie",
            "Dubbed": "false",
            "Host": "",
            "HDTV": "true",
            "Narrator": "",
            "ParentalRating": "",
            "MediaProviderID": "imdb",
            "TotalParts": "0",
            "SeasonPremiere": "false",
            "Actor": "Sharni Vinson -- Erin;Nicholas Tucci -- Felix;Wendy Glenn -- Zee;AJ Bowen -- Crispian;Joe Swanberg -- Drake;Margaret Laney -- Kelly (as Sarah Myers);Amy Seimetz -- Aimee;Ti West -- Tariq;Rob Moran -- Paul;Barbara Crampton -- Aubrey;L.C. Holt -- Lamb Mask;Simon Barrett -- Tiger Mask;Lane Hughes -- Fox Mask;Larry Fessenden -- Erik Harson;Calvin Reeder -- Officer Trubiano;Kate Lyn Sheil -- Talia (uncredited)",
            "Subtitled": "false",
            "Composer": "",
            "EpisodeName": "You're Next",
            "Genre": "Comedy / Horror / Thriller",
            "Director": "Adam Wingard",
            "TagLine": "Did you remember to lock your door?",
            "Taped": "false",
            "SeriesFinale": "false",
            "Voice": "",
            "SeasonNumber": "0",
            "SeriesPremiere": "false",
            "Premiere": "false",
            "Team": "",
            "IMDBID": "tt1853739",
            "MusicalGuest": "",
            "Guest": "",
            "Anchor": "",
            "ScrapedDate": "1389923580527",
            "GuestVoice": "",
            "Choreographer": "",
            "MediaProviderDataID": "tt1853739",
            "Widescreen": "false",
            "ExternalID": "MF10807676",
            "Misc": "",
            "PartNumber": "0",
            "Surround": "false",
            "DD51": "false",
            "Year": "2011",
            "Rated": "R",
            "SAP": "false",
            "Dolby": "false",
            "ChannelPremiere": "false",
            "ExecutiveProducer": "",
            "Producer": "Simon Barrett;Keith Calder;Kim Sherman;Jessica Wu",
            "Correspondent": "",
            "EpisodeNumber": "0",
            "Description": "When the Davison family comes under attack during their wedding anniversary getaway, the gang of mysterious killers soon learns that one of victims harbors a secret talent for fighting back.\n ----\n",
            "ScrapedBy": "Phoenix",
            "Contestant": "",
            "New": "false",
            "OriginalAirDate": "1377230400000",
            "Title": "You're Next",
            "Stereo": "false",
            "X3D": "false",
            "Judge": "",
            "GuestStar": "",
            "Writer": "",
            "CC": "false",
            "Live": "false",
            "RunningTime": "5700000",
            "SeasonFinale": "false",
            "Language": "und",
            "Letterbox": "false",
            "UserRating": "67",
            "MediaTitle": "You're Next"
        },
        "ParentDirectory": "/var/media2/Videos/Movies/New",
        "IsShowFirstRun": false,
        "MediaFileFormatDescription": "Quicktime[H.264/996Kbps 1280x536@24fps, AAC/93Kbps@48kHz Stereo eng]",
        "MediaFileEncoding": "",
        "IsVideoFile": true,
        "NumberOfSegments": 1,
        "IsMusicFile": false,
        "IsTVFile": false,
        "IsThumbnailLoaded": false,
        "FileDuration": 5794120,
        "Size": 792337868,
        "IsLibraryFile": true,
        "IsBluRay": false,
        "IsLocalFile": true,
        "IsCompleteRecording": true,
        "SegmentFiles": [
            "/var/media2/Videos/Movies/New/You're Next (2011).mp4"
        ],
        "MediaFileID": 10807676,
        "IsDVDDrive": false,
        "IsMediaFileObject": true,
        "IsFileCurrentlyRecording": false,
        "IsDVD": false,
        "IsShowReRun": true,
        "FileStartTime": 1389510301880,
        "MediaTitle": "You're Next"
    }
}